lzsslib/__init__.py
lzsslib/compress.py
lzsslib/decompress.py
lzsslib/windowed_buffer.py
lzsslib-0.0.5.dist-info/METADATA
lzsslib-0.0.5.dist-info/WHEEL
lzsslib-0.0.5.dist-info/RECORD
