Metadata-Version: 2.4
Name: lzsslib
Version: 0.0.5
Summary: A library for inflating and deflating LZSS (Lempel, Ziv, Storer, Szymanski) buffers.
Project-URL: Source Code, https://github.com/antoniovazquezblanco/lzsslib/
Project-URL: Issue Tracker, https://github.com/antoniovazquezblanco/lzsslib/issues
Author-email: Antonio Vázquez <antoniovazquezblanco@gmail.com>
Maintainer-email: Antonio Vázquez <antoniovazquezblanco@gmail.com>
License: GPL-3.0-or-later
Classifier: Development Status :: 4 - Beta
Classifier: Intended Audience :: Developers
Classifier: License :: OSI Approved :: GNU General Public License v3 or later (GPLv3+)
Classifier: Operating System :: OS Independent
Classifier: Programming Language :: Python
Requires-Python: >=3.7
Requires-Dist: bitstring>=4.0.1
